<?xml version='1.0' encoding='UTF-8'?>
<bill xmlns="http://xml.house.gov/schemas/uslm/1.0" xmlns:dc="http://purl.org/dc/elements/1.1/" xmlns:dcterms="http://purl.org/dc/terms/" xmlns:xsi="http://www.w3.org/2001/XMLSchema-instance" xsi:schemaLocation="http://xml.house.gov/schemas/uslm/1.0 USLM-1.0.18.xsd" xml:lang="en"><?page 1?><meta><dc:title pagenum="1"> S2107 ENR: Protecting America's Food and Agriculture Act of 2019</dc:title><dc:publisher>U.S. Senate</dc:publisher><dc:date/><dc:format>text/xml</dc:format><dc:language>EN</dc:language><dc:rights>Pursuant to Title 17 Section 105 of the United States Code, this file is not subject to copyright protection and is in the public domain.</dc:rights><dc:creator>Xcential BillDTD to USLM Converter v20200824</dc:creator><property role="congress">One Hundred Sixteenth Congress of the United States of America</property><property role="session">2d Session</property><property role="legis-type">AN ACT</property><property role="legis-num">S. 2107</property><property role="current-chamber">IN THE SENATE OF THE UNITED STATES</property><property role="official-title">To increase the number of CBP Agriculture Specialists and support staff in the Office of Field Operations of U.S. Customs and Border Protection, and for other purposes.</property><property role="docStage">ENR</property><property role="citableAs" value="116s2107enr">116 S. 2107 ENR</property></meta><main id="HDFF605180CCC11EB106309173F13E4C5" name="S2107"><longTitle><content><p>AN ACT</p><p>To increase the number of CBP Agriculture Specialists and support staff in the Office of Field Operations of U.S. Customs and Border Protection, and for other purposes.</p></content></longTitle><enactingFormula>Be it enacted by the Senate and House of Representatives of the United States of America in Congress assembled,</enactingFormula><section identifier="/s1" id="idD498F100E23E4C1F90C40015FACAF5E5" class="bill-dtd-OLC" pagenum="1"><num value="1">Section 1.</num><heading> Short title.</heading><content class="indent0">This Act may be cited as the “<quotedText><shortTitle>Protecting America's Food and Agriculture Act of 2019</shortTitle></quotedText>”.</content></section><section identifier="/s2" id="id7820896DA0554A9D9268C5A521B9B814" class="bill-dtd-OLC" pagenum="1"><num value="2">Sec. 2.</num><heading> Finding.</heading><chapeau class="block">Congress finds that—</chapeau><paragraph identifier="/s2/1" id="id31D1DF30ACA943B59DD5882BD7E4A823" class="bill-dtd-OLC" pagenum="1"><num value="1">(1)</num><content> it is in the national security interest of the United States to ensure that the Nation’s food supply is sufficiently protected; and</content></paragraph><paragraph identifier="/s2/2" id="id583AA96EDDFD4136BA516A348331FFF2" class="bill-dtd-OLC" pagenum="1"><num value="2">(2)</num><content> a vital part of such protection is the availability of adequate resources at the border to conduct inspections of incoming food and agricultural goods.</content></paragraph></section><section identifier="/s3" id="idEE3BF70788604E45A56DECA931511257" class="bill-dtd-OLC" pagenum="1"><num value="3">Sec. 3.</num><heading> Definitions.</heading><chapeau class="block">In this Act:</chapeau><paragraph identifier="/s3/1" id="id543341B5189D469FA8D81477397714E1" class="bill-dtd-OLC" pagenum="1"><num value="1">(1)</num><heading> Appropriate congressional committees.—</heading><chapeau>The term “<term>appropriate congressional committees</term>” means—</chapeau><subparagraph identifier="/s3/1/A" id="id6E93F761FA58418AAEEF6E99300DA21A" class="bill-dtd-OLC" pagenum="1"><num value="A">(A)</num><content> the Committee on Homeland Security and Governmental Affairs of the Senate;</content></subparagraph><subparagraph identifier="/s3/1/B" id="idE461475B720E4EB0A1A5E9ABCDB81147" class="bill-dtd-OLC" pagenum="1"><num value="B">(B)</num><content> the Committee on Agriculture, Nutrition, and Forestry of the Senate;</content></subparagraph><subparagraph identifier="/s3/1/C" id="id4F6F392E71704443B0B6EDE0DB50A59C" class="bill-dtd-OLC" pagenum="1"><num value="C">(C)</num><content> the Committee on Homeland Security of the House of Representatives; and</content></subparagraph><subparagraph identifier="/s3/1/D" id="idF148A94F925A41C0BE199BBF3282120F" class="bill-dtd-OLC" pagenum="1"><num value="D">(D)</num><content> the Committee on Agriculture of the House of Representatives.</content></subparagraph></paragraph><paragraph identifier="/s3/2" id="id385A48AAF7FC4910AA5EE9CC96DB5F4D" class="bill-dtd-OLC" pagenum="1"><num value="2">(2)</num><heading> CBP.—</heading><content>The term “<term>CBP</term>” means U.S. Customs and Border Protection.</content></paragraph></section><section identifier="/s4" id="id0346E42608FB48F1B082BEEAC202B3FC" class="bill-dtd-OLC" pagenum="1"><num value="4">Sec. 4.</num><heading> Additional U.S. Customs and Border Protection personnel.</heading><subsection identifier="/s4/a" id="id153A083D820D4A4993F67FE8EC2D3F20" class="bill-dtd-OLC" pagenum="1"><num value="a">(a)</num><heading> CBP Agriculture Specialists.—</heading><content>The Commissioner of U.S. Customs and Border Protection may hire, train, and assign 240 new CBP Agriculture Specialists above the current attrition level during every fiscal year until the total number of CBP Agriculture Specialists equals and sustains the requirements identified each year in the Agriculture Resource Allocation Model.</content></subsection><subsection identifier="/s4/b" id="idA6A2DD35DF7843398210CC8FB613240A" class="bill-dtd-OLC" pagenum="1"><num value="b">(b)</num><heading> Mission and operational support staff.—</heading><?page 2?><paragraph identifier="/s4/b/1" id="idB5E2D5021EBB4708A1A20E02AF85FCED" class="bill-dtd-OLC" pagenum="2"><num value="1">(1)</num><heading> In general.—</heading><content>The Commissioner of U.S. Customs and Border Protection may hire, train, and assign support staff to support CBP Agriculture Specialists.</content></paragraph><paragraph identifier="/s4/b/2" id="id82F514D38D6B43BFA7855DA7082DB93A" class="bill-dtd-OLC" pagenum="2"><num value="2">(2)</num><heading> CBP agriculture technicians.—</heading><content>The Commissioner of U.S. Customs and Border Protection may hire, train, and assign 200 new CBP Agriculture Technicians during each fiscal year until the total number of CBP Agriculture Technicians equals and sustains the requirements identified each year in the Mission and Operational Support Resource Allocation Model.</content></paragraph></subsection><subsection identifier="/s4/c" id="id462E705AD27642438FBAD66FA5D54EC1" class="bill-dtd-OLC" pagenum="2"><num value="c">(c)</num><heading> CBP agriculture canine teams.—</heading><content>The Commissioner of U.S. Customs and Border Protection may hire, train, and assign 20 new CBP agriculture canine teams during each of the first 3 fiscal years beginning after the date of the enactment of this Act.</content></subsection><subsection identifier="/s4/d" id="id9D969BA7EE4F436DBCB836087B23D4ED" class="bill-dtd-OLC" pagenum="2"><num value="d">(d)</num><heading> Traffic forecasts.—</heading><chapeau>In calculating the number of CBP Agriculture Specialists needed at each port of entry through the Agriculture Resource Allocation Model, the Office of Field Operations shall—</chapeau><paragraph identifier="/s4/d/1" id="id41003CFE0E0741199B43CB6C4DEC030D" class="bill-dtd-OLC" pagenum="2"><num value="1">(1)</num><content> rely on data collected regarding the inspections and other activities conducted at each such port of entry; and</content></paragraph><paragraph identifier="/s4/d/2" id="id9F6ECF748E774C8E90661FA08A474B13" class="bill-dtd-OLC" pagenum="2"><num value="2">(2)</num><content> consider volume from seasonal surges, other projected changes in commercial and passenger volumes, the most current commercial forecasts, and other relevant information.</content></paragraph></subsection><subsection identifier="/s4/e" id="id3F10EB48C6EF4453A1043CCECAF8664C" class="bill-dtd-OLC" pagenum="2"><num value="e">(e)</num><heading> Authorization of appropriations.—</heading><paragraph identifier="/s4/e/1" id="idCD0A96106FF649DE9715AE53BC39DC80" class="bill-dtd-OLC" pagenum="2"><num value="1">(1)</num><heading> CBP agriculture specialists.—</heading><chapeau>There is authorized to be appropriated to carry out subsection (a)—</chapeau><subparagraph identifier="/s4/e/1/A" id="id3463219657B249479EB2902600197517" class="bill-dtd-OLC" pagenum="2"><num value="A">(A)</num><content> $29,900,000 for fiscal year 2020;</content></subparagraph><subparagraph identifier="/s4/e/1/B" id="id791C3E0376AD4BDB8217E81B3D9C69C2" class="bill-dtd-OLC" pagenum="2"><num value="B">(B)</num><content> $36,100,000 for fiscal year 2021; and</content></subparagraph><subparagraph identifier="/s4/e/1/C" id="idB1CFFEE3D06E4A9584A2D225FB96A516" class="bill-dtd-OLC" pagenum="2"><num value="C">(C)</num><content> $40,500,000 for fiscal year 2022.</content></subparagraph></paragraph><paragraph identifier="/s4/e/2" id="id835C975A42C54E2B808AEE814626C9D7" class="bill-dtd-OLC" pagenum="2"><num value="2">(2)</num><heading> CBP agriculture technicians.—</heading><chapeau>There is authorized to be appropriated to carry out subsection (b)—</chapeau><subparagraph identifier="/s4/e/2/A" id="idACC9D53CDCD44CCCB6FD76522D49B2EA" class="bill-dtd-OLC" pagenum="2"><num value="A">(A)</num><content> $11,000,000 for fiscal year 2020;</content></subparagraph><subparagraph identifier="/s4/e/2/B" id="idEFB9C82029E04C628603769DB1D5082C" class="bill-dtd-OLC" pagenum="2"><num value="B">(B)</num><content> $25,000,000 for fiscal year 2021; and</content></subparagraph><subparagraph identifier="/s4/e/2/C" id="id29F07D9962E542398966E672ECBB4130" class="bill-dtd-OLC" pagenum="2"><num value="C">(C)</num><content> $38,000,000 for fiscal year 2022.</content></subparagraph></paragraph><paragraph identifier="/s4/e/3" id="idC0B59B999BD74417A8750504C3515029" class="bill-dtd-OLC" pagenum="2"><num value="3">(3)</num><heading> CBP agriculture canine teams.—</heading><chapeau>There is authorized to be appropriated to carry out subsection (c)—</chapeau><subparagraph identifier="/s4/e/3/A" id="idFF9D8D0D07F64614A9C5A680E1F09382" class="bill-dtd-OLC" pagenum="2"><num value="A">(A)</num><content> $3,500,000 for fiscal year 2020;</content></subparagraph><subparagraph identifier="/s4/e/3/B" id="id65579D6D0E704408950EEC0407C4D4E9" class="bill-dtd-OLC" pagenum="2"><num value="B">(B)</num><content> $7,400,000 for fiscal year 2021; and</content></subparagraph><subparagraph identifier="/s4/e/3/C" id="id559FBE349589492DB4961A0728CF3AC4" class="bill-dtd-OLC" pagenum="2"><num value="C">(C)</num><content> $12,200,000 for fiscal year 2022.</content></subparagraph></paragraph><paragraph identifier="/s4/e/4" id="id2941DD577ABB400782274A364D13C0AC" class="bill-dtd-OLC" pagenum="2"><num value="4">(4)</num><heading> Training.—</heading><content>There is authorized to be appropriated for training costs associated with the new CBP personnel and canine teams hired pursuant to subsections (a), (b), and (c) $6,000,000 for each of the fiscal years 2020, 2021, and 2022.</content></paragraph></subsection></section><section identifier="/s5" id="id0C2B9E7E3EF44D4592F7E83CE64FF077" class="bill-dtd-OLC" pagenum="2"><num value="5">Sec. 5.</num><heading> GAO study, briefing, and report.</heading><subsection identifier="/s5/a" id="idB141E6725BB74555A255312B71320C18" class="bill-dtd-OLC" pagenum="2"><num value="a">(a)</num><heading> Study.—</heading><chapeau>The Comptroller General of the United States, after consultation with the appropriate congressional committees, shall conduct a review of the efforts of the Department of Homeland Security, the Department of Agriculture, and other Federal agencies to address risks to the agricultural supply that analyzes—</chapeau><paragraph identifier="/s5/a/1" id="id901F24207A7A4DF29803D6CE80DC92F4" class="bill-dtd-OLC" pagenum="2"><num value="1">(1)</num><content> interagency coordination and the distribution of responsibilities among Federal agencies with respect to the inspection of agricultural commodities entering the United States;</content></paragraph><paragraph identifier="/s5/a/2" id="idAD8F0D3DD893455BA43D1EBE120CED63" class="bill-dtd-OLC" pagenum="2"><num value="2">(2)</num><content> the effectiveness of such inspection responsibilities among Federal agencies; and</content></paragraph><?page 3?><paragraph identifier="/s5/a/3" id="idA30903A0AB304B24B23F16DE536C3F5D" class="bill-dtd-OLC" pagenum="3"><num value="3">(3)</num><content> the training provided to, and working conditions of, CBP Agriculture Specialists.</content></paragraph></subsection><subsection identifier="/s5/b" id="id56F65B508F034E4A9C53EDB9E6223FB6" class="bill-dtd-OLC" pagenum="3"><num value="b">(b)</num><heading> Briefing.—</heading><content>Not later than 1 year after the date of the enactment of this Act, the Comptroller General shall brief the appropriate congressional committees regarding the results of the study conducted pursuant to subsection (a).</content></subsection><subsection identifier="/s5/c" id="idB4B6EF4A8AB943C0AA81842675057F75" class="bill-dtd-OLC" pagenum="3"><num value="c">(c)</num><heading> Report.—</heading><content>Not later than 90 days after the briefing required under subsection (b), the Comptroller General shall complete the study required under subsection (a) and make the results of the study available to the public.</content></subsection></section></main><signatures><signature><name/><role>Speaker of the House of Representatives</role></signature><signature><name/><role>Vice President of the United States and President of the Senate</role></signature></signatures></bill>